{
    "LEFT_PANE": {
        "MAP": {
            "TITLE": "Organiser",
            "EMPTY_TITLE": "Commencez à créer !",
            "EMPTY_DESCRIPTION": "Créez et organisez votre Story ici",
            "TOOLTIP": "Organiser",
            "MINIMUM_READ_TIME_LABEL": "min. de lecture"
        },
        "VISIBILITY": {
            "TITLE": "Visibilité",
            "DESCRIPTION": "Qui peut voir votre Story",
            "LANGUAGE_TITLE": "Langue",
            "LANGUAGE_DESCRIPTION": "Sélectionner la langue",
            "LANGUAGE_CHECKBOX_LABEL": "Autoriser la traduction dans d'autres langues",
            "SPONSORED_TITLE": "Contenu sponsorisé",
            "SPONSORED_CHECKBOX_LABEL": "Ceci est une Story sponsorisée",
            "TOOLTIP": "Visibilité : {{viewPermission}}",
            "VIEW_PERMISSIONS_DROPDOWN": {
                "PUBLIC": "Public (recommandé)",
                "ONLY_ME": "Uniquement moi",
                "ONLY_DIRECT_LINK": "Lien privé uniquement"
            }
        },
        "TAGS": {
            "TITLE": "Mots clés",
            "DESCRIPTION": "Mettez des mots clés à votre Story pour mieux la référencer",
            "TOOLTIP": "Mots clés",
            "NEW_TAG_PLACEHOLDER": "Entrer vos propres mots clés",
            "NEW_TAG_DESCRIPTION": "Séparez-les par une virgule"
        },
        "SOCIAL": {
            "TITLE": "Réseaux Sociaux",
            "DESCRIPTION": "Comment votre Story apparaîtra sur les réseaux sociaux",
            "TOOLTIP": "Réseaux Sociaux"
        },
        "ABOUT": {
            "TITLE": "Qu'est ce qu'une Story ?",
            "DESCRIPTION": "Story est le premier outil de création d'article qui permet aux équipes éditoriales de découper leurs récits en plusieurs contenus engageants, intéractifs et visuels.",
            "STEP_1": "Rédiger votre Story",
            "STEP_2": "Publier",
            "STEP_3": "Coller le code Embed directement sur votre site",
            "STEP_4": "Fini !",
            "QUESTIONS_TITLE": "Si vous avez des questions :",
            "QUESTIONS_DESCRIPTION": "on est là !",
            "TOOLTIP": "À propos"
        }
    },
    "ACTION_PANE": {
        "PUBLISH_BUT": "Publier",
        "SAVE_BUT": "Enregistrer",
        "ERROR_MESSAGE": "Erreur",
        "PUBLISH_BUT_PENDING": "Publication en cours...",
        "PREVIEW_BUT": "Prévisualiser",
        "SAVED_NOTIFICATION": "Enregistré",
        "VIEW_LINK": "Voir",
        "SAVE_BUT_NEW_ITEM": "Sauvegarder brouillon",
        "SAVE_BUT_PENDING": "Sauvegarde en cours...",
        "ERROR": {
            "MISSING_REQUIREMENTS": "Tous les critères ne sont pas remplis",
            "SAVING_DISABLED": "Sauvegarde impossible. Merci de réessayer dans 5 minutes.",
            "OUTDATED": "L'item a expiré",
            "SAVE_FAILED": "Echec de l'enregistrement",
            "COVER_UNSUPPORTED_FORMAT": "Échec du chargement de la photo de couverture. Essayez un autre fichier.",
            "LOGGED_OUT": "Merci de vous reconnecter",
            "BLOCKED": "Votre compte utilisateur est bloqué"
        },
        "PREVIEW_BUT_PENDING": "Recherche...",
        "UNSAVED_DRAFT": "Brouillon non sauvegardé"
    },
    "DESCRIPTION_PLACEHOLDER": "Description",
    "DELETE_SECTION_MESSAGE": "Êtes-vous sûr(e) ?",
    "MODAL_LANGUAGE": {
        "NEW_LABEL": "NOUVEAU",
        "TITLE": "Sélectionnez votre langue de préférence",
        "DONE_BUT": "Terminé"
    },
    "ONBOARDING": {
        "GALLERY_OPEN_LABEL": "Voir des exemples",
        "CONVO": {
            "TITLE_LABEL": "Donnez l'impression aux lecteurs qu'ils lisent une conversation SMS ou de messagerie instantannée.",
            "TEXT_1_LABEL": "Créer les participants de la conversation (photos de profil et noms) puis faites les converser en créant autant de bulles de dialogue que vous voulez ! Ajoutez-y des images et des GIFs si vous le souhaitez.",
            "TEXT_2_LABEL": "Choisissez le template Convo que vous souhaitez. Par exemple, ici le template \"conversation messenger iOS\".",
            "TEXT_3_LABEL": "Utilisez Convo pour créer une liste ou la timeline d'un évènement. Téléchargez simplement des numéros ou des dates en photo de profil de chaque \"participant\"."
        },
        "FLIP_CARD": {
            "TITLE_LABEL": "Surprenez vos lecteurs en affichant des images ou du texte qui se retournent par un simple clic.",
            "TEXT_1_LABEL": "TEXT_1_LABEL",
            "TEXT_2_LABEL": "Utilisez les Flip Card pour révéler quelque chose de surprenant, distrayant ou choquant à vos lecteurs. Une bonne manière d'exploiter les Flip Card est aussi la confrontation avant/après.",
            "TEXT_3_LABEL": "Utilisez les Flip Card pour filtrer ce que les lecteurs peuvent voir. Donnez leur le choix, par exemple, d'accéder ou non à des contenus réservés aux adultes."
        },
        "PARAGRAPH": {
            "TITLE_LABEL": "Utilisez la fonction texte pour structurer votre Story.",
            "TEXT_1_LABEL": "Utilisez le surligneur pour mettre en avant le plus important.",
            "TEXT_2_LABEL": "Vos yeux seront immédiatement attirés par le texte surligné. Assurez-vous donc que les informations les plus importantes sont surlignées.",
            "TEXT_3_LABEL": "Ajoutez des emojis et des liens pour rendre votre texte plus intéractif et vivant."
        },
        "POLL": {
            "TITLE_LABEL": "Le sondage (Poll) permet au lecteur d'exprimer son opinion et de réagir à votre contenu.",
            "TEXT_1_LABEL": "Utilisez l'outil Poll pour impliquer votre lecteur et lui demander son avis. Par exemple, demandez lui ce qu'il pense de quelque chose en rapport avec les réseaux sociaux.",
            "TEXT_2_LABEL": "Ajoutez une image d'illustration à votre sondage pour lui donner plus d'impact visuel.",
            "TEXT_3_LABEL": "Ajoutez une image d'illustration et utilisez le template Grid pour créer un sondage captivant auquel on a envie de réagir !",
            "TEXT_4_LABEL": "Pensez à toujours inclure la réponse \"aucune des réponses ci-dessus\" pour ne pas obliger le lecteur à choisir une réponse qui ne lui convient pas.",
            "TEXT_5_LABEL": "TEXT_5_LABEL",
            "TEXT_6_LABEL": "Vous pouvez cacher le résultat d'un sondage et le dévoiler à votre audience seulement au moment propice."
        },
        "QUOTE": {
            "TITLE_LABEL": "Mettez en avant des paroles inspirantes en utilisant le module de citation (Quote).",
            "TEXT_1_LABEL": "Concises et touchantes, faites des citations impactantes et faciles à lire.",
            "TEXT_2_LABEL": "Ajoutez la photo de l'auteur de la citation pour donner plus d'informations et de contexte."
        },
        "SUMMARY": {
            "TITLE_LABEL": "Le module Summary va droit au but et permet de donner au lecteur uniquement les informations dont il a besoin. Ce template peut s'utiliser de plein de manières différentes...",
            "TEXT_1_LABEL": "Utilisez Summary pour lister les principaux enjeux d'un sujet. Donnez à votre audience une vue d'ensemble grâce à une courte énumération. Insérez une image d'illustration pour relier votre Summary au sujet de votre article.",
            "TEXT_2_LABEL": "Privilégiez le template Summary avec la barre sur le côté pour les ingrédients quand vous voulez écrire une recette. Ajoutez une belle photo du plat à votre Summary et il deviendra plus alléchant.",
            "TEXT_3_LABEL": "Utilisez les cases à cocher pour donner un effet de to-do list à votre Summary."
        },
        "VIDEO_CREATOR": {
            "TITLE_LABEL": "Créer des vidéos en toute simplicité. Utilisez nos templates déjà tout prêts, choisissez simplement les couleurs et les musiques en fonction de votre sujet.",
            "TEXT_1_LABEL": "Privilégiez le template Classique pour créer une vidéo avec un effet catalogue où vous pourrez intégrer des GIFs, vos images et vos vidéos.",
            "TEXT_2_LABEL": "Utilisez le template VS pour confronter et révéler les contrastes entre deux éléments d'un sujet.",
            "TEXT_3_LABEL": "Chaque diapositive dans le template VS comparera un sous-thème du thème général grâce à des images, des GIFs, du texte ou même des vidéos !",
            "TEXT_4_LABEL": "Utilisez le template Facts pour lister des faits marquants sur un sujet important pour vos lecteurs.",
            "TEXT_5_LABEL": "Chaque diapositive dans le template Facts possède une large zone de texte par dessus l'image de fond.",
            "TEXT_6_LABEL": "Utilisez le template Swift pour créer une vidéo plus rapide avec une diapositive d'introduction annonçant visuellement les prochaines diapositives de la vidéo."
        },
        "QUIZ": {
            "TEXT_1_LABEL": "Éclairez les lecteurs sur ce qui les intéressent le plus - eux-mêmes. ",
            "TEXT_2_LABEL": "Choisissez une palette de couleur pour votre test de personnalité.",
            "TEXT_3_LABEL": "Insérer des vidéos and des GIFs.",
            "TEXT_4_LABEL": "TEXT_4_LABEL",
            "TITLE_LABEL": "Personnalisez"
        },
        "TRIVIA": {
            "TEXT_1_LABEL": "Inclure des vidéos et des GIFs",
            "TEXT_2_LABEL": "Inclure un \"call-to-action\"",
            "TEXT_3_LABEL": "Donner à vos lecteurs des informations supplémentaires",
            "TEXT_4_LABEL": "Donner à vos lecteurs des informations supplémentaires",
            "TITLE_LABEL": "Défiez vos lecteurs !"
        },
        "MEDIA": {
            "TITLE_LABEL": "Rechercher, télécharger, copier des liens à ajouter à vos créations vidéos, images, GIFS et posts.",
            "TEXT_1_LABEL": "Flouter des images pour rajouter une touche de mystère, ou cacher des spoilers.",
            "TEXT_2_LABEL": "Add movement to your image with the zoom-in effect.",
            "TEXT_3_LABEL": "Use the blur effect to give readers the choice to decide if they want to see graphic content or not.",
            "TEXT_4_LABEL": "Embed Google Maps to share specific locations.",
            "TEXT_5_LABEL": "Include any video from Vimeo or YouTube.",
            "TEXT_6_LABEL": "Embed Twitter posts to make your content more interesting and engaging.",
            "TEXT_7_LABEL": "Embed Instagram posts to make your content more visually stunning.",
            "TEXT_8_LABEL": "Use any video on Vimeo to make your article more interesting.",
            "TEXT_9_LABEL": "Use any video on Youtube to make your article more interesting."
        }
    },
    "TEMPLATES": {
        "START_NEW": "Créer un nouveau template",
        "UPDATED": "Nouveautés",
        "TEMPLATE_NAME": "A à Z",
        "NEW": "Nouveau",
        "NEW_FROM_TEMPLATE": "Nouveaux Templates",
        "DUPLICATE": "Dupliquer",
        "ADD_A_TEMPLATE": "Ajouter aux templates",
        "ADDED_A_TEMPLATE": "Ajouté !",
        "ADDING": "Ajout en cours...",
        "ADDING_DISABLED": "Pour dupliquer ou pour ajouter un template, sauvegardez le brouillon",
        "SOMETHING_WENT_WRONG": "Une erreur est survenue :(",
        "PLEASE_TRY_AGAIN": "Merci de réessayer",
        "CREATE": "Créer",
        "INCLUDES": "INSÉRER",
        "DELETE": "Supprimer",
        "DELETE_FROM_LIST": "Êtes-vous sûr(e) de vouloir supprimer ce template ?",
        "CREATING_IN_PLAYBUZZ": "Créer avec Playbuzz devient plus simple",
        "CREATING_IN_PLAYBUZZ_2": "Créer n'a jamais été aussi facile...",
        "CREATING_IN_PLAYBUZZ_2_DESC": "Racontez votre histoire depuis un template déjà fait ou créez le vôtre.",
        "CREATING_IN_PLAYBUZZ_DESC_1": "Pour créer un nouveau template, cliquez sur Créer et choisissez l'option",
        "CREATING_IN_PLAYBUZZ_DESC_2": "> Ajouter aux templates",
        "START_HERE": "Commencez ici !",
        "NO_TEMPLATES_FOUND": "Aucun template correspondant",
        "CREATE_A_TEMPLATE": "Créer un template",
        "GOT_IT": "Compris !",
        "FEATURED": "Featured",
        "TRAVEL": "Voyage",
        "HOLIDAY": "Vacances",
        "FUN": "Fun",
        "STYLE": "Style",
        "MUSIC": "Musique",
        "SPORTS": "Sport",
        "ENTERTAINMENT": "Divertissement",
        "NEWS": "Actus",
        "FOOD": "Cuisine",
        "WORKING_ON_TEMPLATE": "Edition en cours :",
        "VIDEO": "Vidéo"
    },
    "CONVO": {
        "PARTICIPANT_PLACEHOLDER": "Participant",
        "BUBBLE_CONTENT_PLACEHOLDER": "Entrer un texte...",
        "ADD_BUBBLE_TOOLTIP": "Ajouter une bulle",
        "ADD_PARTICIPANT_TOOLTIP": "Ajouter participant",
        "DELETE_MESSAGE": "Êtes-vous sûr(e) ?",
        "ADD_SECTION_TOOLTIP": "Convo"
    },
    "CREATE_MODULES": {
        "TEXT_EDITOR": {
            "WORD": "MOTS",
            "WORDS": "MOTS",
            "GOOD": "BIEN",
            "NORMAL": "O.K",
            "BAD": "UN PEU TROP LONG",
            "BOLD_TOOLTIP": "Gras",
            "GOOD_INDICATION": "BIEN",
            "NORMAL_INDICATION": "O.K",
            "BAD_INDICATION": "UN PEU TROP LONG",
            "MINIMUM_READ_TIME_LABEL": "{{readTime}} min. de lecture"
        },
        "SECTION_TITLE_PLACEHOLDER": "Titre",
        "NOT_SAVED_ERR_MESSAGE": "Les dernières modifications n'ont pas été sauvegardées. Êtes-vous sûr(e) de vouloir quitter ?",
        "LIST": {
            "ENABLE_VOTING_SWITCH": "Activer les votes",
            "VOTE": "Vote",
            "TYPE": {
                "NONE": "Normal",
                "NUMBER": "Numérotation",
                "BULLET": "Puces",
                "RANK": "Liste dynamique (vote)",
                "DOWN": "Vote négatif"
            },
            "ENABLE_DOWN_VOTE": "Autoriser le vote négatif",
            "DISABLE_DOWN_VOTE": "Désactiver le vote négatif",
            "DISABLE_VOTING_SWITCH": "Fermer les votes"
        }
    },
    "CTA": {
        "NO_EFFECT": "Aucun",
        "PULSE_EFFECT": "Animé",
        "FLOATING_EFFECT": "Flottant",
        "BUTTON_TEXT": "Entrer texte...",
        "LINK_PLACEHOLDER": "Entrer lien...",
        "TEST_LINK_TOOLTIP": "Tester le lien",
        "ADD_SECTION_TOOLTIP": "CTA",
        "APPLE_LINK_PLACEHOLDER": "Lien iOS (optionnel)",
        "ANDROID_LINK_PLACEHOLDER": "Lien Android (optionnel)",
        "WEB_LINK_TOOLTIP": "Universel",
        "APPLE_LINK_TOOLTIP": "iOS",
        "ANDROID_LINK_TOOLTIP": "Android"
    },
    "EMBED": {
        "DESCRIPTION_PLACEHOLDER": "Description",
        "ADD_SECTION_TOOLTIP": "Importer depuis Internet"
    },
    "IMAGE": {
        "CAPTION": "Image",
        "ADD_SECTION_TOOLTIP": "Image"
    },
    "PARAGRAPH": {
        "EDITOR_PLACEHOLDER": "Paragraphe",
        "ADD_SECTION_TOOLTIP": "Texte"
    },
    "POLL": {
        "BACKGROUND_TEMPLATE_TOOLTIP": "Image d'arrière plan",
        "COVER_TEMPLATE_TOOLTIP": "Image d'illustration",
        "CLASSIC_TEMPLATE_TOOLTIP": "Résultats classiques",
        "GRID_TEMPLATE_TOOLTIP": "Grille de résultat",
        "SETTINGS_TOOLTIP": "Paramètres du sondage",
        "TITLE_PLACEHOLDER": "Question",
        "OPTION_PLACEHOLDER": "réponse {{index}}",
        "ADD_OPTION_BUT": "Ajouter une réponse",
        "SETTINGS": {
            "TITLE": "PARAMÈTRES DU SONDAGE",
            "HERE_LINK": "Ici",
            "BACK_BUTTON": "Retour à l'édition",
            "ENABLE_VOTING_SWITCH": "Activer les votes",
            "TOTAL_VOTES_SWITCH": "Afficher le nombre total de votes",
            "DISPLAY_LOGO_SWITCH": "Afficher Logo",
            "DISPLAY_LOGO_DESCRIPTION": "Personnalisez encore plus votre sondage en ajoutant votre logo. Remplacez l'image de présentation",
            "END_CARD_SWITCH": "End Card",
            "END_CARD_DESCRIPTION": "Générer plus de partages et d'engagements en utilisant End Card",
            "END_CARD": {
                "TITLE_LABEL": "Titre",
                "TITLE_PLACEHOLDER": "Entrer le titre",
                "DESCRIPTION_LABEL": "Description",
                "DESCRIPTION_PLACEHOLDER": "Entrer une description..."
            },
            "ALLOW_REVOTES_SWITCH": "Possibilité de re-voter chaque jour",
            "HIDE_RESULTS_SWITCH": "Cacher les résultats du sondage",
            "SECURED_SWITCH": "Activer sécurité sondage",
            "ADDITIONAL_SETTINGS_WARNING": "Cette modification sera visible après avoir enregistré."
        },
        "CLASSIC_LAYOUT_TOOLTIP": "Barres classiques",
        "GRID_LAYOUT_TOOLTIP": "Vignettes rondes",
        "DELETE_OPTION_BUT": "Supprimer cette réponse",
        "SQUARE_LAYOUT_TOOLTIP": "Vignettes Carrées",
        "ADD_SECTION_TOOLTIP": "Poll"
    },
    "QUOTE": {
        "TEXT_PLACEHOLDER": "Entrer une citation",
        "QUOTEE_PLACEHOLDER": "Qui en est l'auteur ?",
        "ADDITIONAL_TEXT_PLACEHOLDER": "Plus de détails",
        "ADD_SECTION_TOOLTIP": "Citation"
    },
    "SUMMARY": {
        "ADD_ROW": "Ajouter une ligne",
        "SUBTITLE_PLACEHOLDER": "Sous-titre",
        "ROW_PLACEHOLDER": "Entrer du texte...",
        "NO_EFFECT": "Aucun",
        "FADE_EFFECT": "Estomper",
        "TITLE_PLACEHOLDER": "Titre",
        "ADD_SECTION_TOOLTIP": "Résumé"
    },
    "VIDEO_CREATOR": {
        "PLAY": "PLAY",
        "PAUSE": "PAUSE",
        "GALLERY_TITLE": "Choisissez un template",
        "OPEN_TEMPLATES_GALLERY_BUT": "Changer de template",
        "CLOSE_TEMPLATES_GALLERY_BUT": "Retour à l'édition",
        "SETTINGS": {
            "TITLE": "Paramètres",
            "AUTOPLAY_SWITCH_LABEL": "Autoplay",
            "MUTE_SWITCH_LABEL": "Autoplay (muet)",
            "LOGO_LABEL": "Personnaliser le logo",
            "CLOSE_SETTINGS": "Retour à l'édition",
            "LOGO_DESCRIPTION": "Téléchargez votre propre logo qui apparaîtra en fin de vidéo.",
            "ENABLE_LOGO_ACROSS_VIDEO": "Présence du logo pendant la vidéo"
        },
        "PREVIEW_BUT": "Générer la vidéo",
        "NOT_SUPPORTED_LABEL": "Non pris en charge",
        "IE_ERR_MESSAGE": "La création de la vidéo n'est pas prise en charge par Internet Explorer. Utilisez Chrome pour profiter de toutes les fonctionnalités ! Vous pouvez quand même publier votre item sur Internet Explorer et votre vidéo sera prête dans un instant.",
        "REMOVE_SCENE": {
            "TITLE": "Êtes-vous certain(e) ?",
            "DELETE_BUTTON_TEXT": "Supprimer"
        },
        "SCENE_NAME": {
            "GENERAL": {
                "INTRO_LABEL": "INTRO",
                "ENDING_LABEL": "FIN",
                "CREDITS_LABEL": "CRÉDITS"
            },
            "CLASSIC": {
                "ITEM_LABEL": "ITEM"
            },
            "FACTS": {
                "ITEM_LABEL": "FACT"
            },
            "SWIFT": {
                "ITEM_BOTTOM_LABEL": "EN BAS",
                "ITEM_TOP_LABEL": "AU HAUT"
            },
            "VS": {
                "ITEM_LABEL": "THÈME",
                "ENDING_LABEL": "CONCLUSION"
            }
        },
        "CHANGE_TEMPLATE_WARNING": {
            "TITLE": "Type de template différent",
            "WARNING_MESSAGE": "Le contenu déjà chargé ne s'affichera peut-être pas dans ce template",
            "CANCEL_BUTTON": "Annuler",
            "CHANGE_BUTTON": "Changer de template"
        },
        "AUDIO_LABEL": {
            "NONE": "Aucun",
            "CINEMATIC": "Cinématographique",
            "CANCEL_BTN": "Annuler",
            "SELECT_BTN": "Selectionner",
            "CORPORATE": "Corporate",
            "POSITIVE_AND_UPBEAT": "Positive & Upbeat",
            "ACOUSTIC": "Acoustique",
            "HIGH_ENERGY": "High Energy",
            "EPIC": "Héroïque"
        },
        "TEMPLATE_NAME": {
            "CLASSIC": "Classique",
            "VS": "VS",
            "SWIFT": "Swift",
            "FACTS": "Facts"
        },
        "THEME_NAME_LABEL": {
            "DEFAULT": "Défaut",
            "PLAYBUZZ": "Playbuzz",
            "SHADES_OF_GRAY": "Grey",
            "PLAYTIME": "Playtime",
            "BACK_TO_SCHOOL": "Back to School",
            "NEUTRAL_BLUE": "Neutral Blue",
            "PHAEDRA": "Phaedra",
            "FIESTA": "Fiesta",
            "GREENS": "Greens",
            "BUBBLEGUM": "Bubblegum",
            "GROUND_CONTROL": "Ground Control",
            "AMERICA": "America",
            "BEACH_UMBRELLA": "Beach Umbrella",
            "BEACH_TIME": "Beach Time",
            "GOSSIP": "Gossip"
        },
        "TEMPLATES": {
            "GENERAL": {
                "MAIN_TITLE_PLACEHOLDER": "Entrer titre principal",
                "ENTER_TEXT_PLACEHOLDER": "Entrer Texte",
                "CTA_PLACEHOLDER": "Terminer avec un \"call to action\" !",
                "BACKGROUND_REQUIRED_VALIDATION_MSG": "Une image de fond est obligatoire",
                "TEXT_REQUIRED_VALIDATION_MSG": "Le texte est obligatoire",
                "TITLE_REQUIRED_VALIDATION_MSG": "Le titre est obligatoire"
            },
            "CLASSIC": {
                "SUB_TITLE_PLACEHOLDER": "Entrer un sous-titre (optionnel)"
            },
            "VS": {
                "PRE_CTA_PLACEHOLDER": "Entrer un texte préliminaire (optionnel)",
                "SIDE_A_PLACEHOLDER": "A",
                "FEATURE_A_PLACEHOLDER": "Entrer le texte pour A",
                "SIDE_B_PLACEHOLDER": "B",
                "FEATURE_B_PLACEHOLDER": "Entrer le texte pour B",
                "PREMISE_PLACEHOLDER": "Entrer le titre de la vidéo",
                "COMPARISON_PLACEHOLDER": "Comparaison",
                "A_BACKGROUND_REQUIRED_VALIDATION_MSG": "L'image de fond A est obligatoire",
                "B_BACKGROUND_REQUIRED_VALIDATION_MSG": "L'image de fond B est obligatoire",
                "A_TITLE_REQUIRED_VALIDATION_MSG": "Le titre A est obligatoire",
                "B_TITLE_REQUIRED_VALIDATION_MSG": "Le titre B est obligatoire",
                "PREMISE_REQUIRED_VALIDATION_MSG": "Le titre de la vidéo est obligatoire",
                "COMPARISON_REQUIRED_VALIDATION_MSG": "La comparaison est obligatoire"
            },
            "FACTS": {
                "ENTER_TITLE_PLACEHOLDER": "Entrer le titre",
                "ENTER_FACT_PLACEHOLDER": "Entrer un fait",
                "FACT_REQUIRED_VALIDATION_MSG": "Un fait est obligatoire"
            }
        },
        "ADD_SECTION_TOOLTIP": "Créer une vidéo",
        "ERROR_OCCURRED_HEADER": "Une erreur est survenue",
        "OK": "OK",
        "MISSING_CONTENT": "Merci de d'abord entrer le contenu",
        "CATEGORIES_NAMES": {
            "MAGICAL": "Magique",
            "LISTS": "Liste",
            "COMPARISON": "Comparaison"
        },
        "TOOLTIPS": {
            "LAYOUT_SELECTION": "Mise en forme",
            "FONT": "Police",
            "ADD_ITEM": "Ajouter un item",
            "PATTERN": "Pattern",
            "MUSIC": "Musique",
            "COLOR": "Couleur",
            "SETTINGS": "Paramètres",
            "BACKGROUND_OPTIONS": "Arrière-plan",
            "NONE": "Aucun",
            "SOLID": "Solide",
            "SEMI_TRANSPARENT": "Semi-transparent",
            "TEXT_BACKGROUND_BLOCKS": "Texte Surligné",
            "BLUR": "Flou",
            "SQUARE": "Carré",
            "ROUND": "Rond",
            "SKEW": "Oblique",
            "DIAMOND": "Diamant",
            "COLOR_THEME": "Thème couleur",
            "SCENE_DURATION": "Durée de la scène"
        },
        "AUTO_DURATION": "Durée automatique",
        "BTN_INTRO_BUBBLE": {
            "NEW": "NOUVEAU !",
            "TITLE": "Création de vidéos - Nouveauté !",
            "DESC": "Découvrez notre nouvel outil de création vidéo intelligent",
            "DECLINE": "Plus tard",
            "ACCEPT": "Montrez-moi"
        },
        "SECTION_INTRO_BUBBLE": {
            "NEW": "NOUVEAU !",
            "TITLE": "Un contenu important mérite une belle vidéo.",
            "DESC": "Ajoutez du contenu puis cliquez sur \"Optimiser et aperçu\". Notre algorithme d'Intelligence Artificielle vous propose alors la meilleure mise en page pour votre vidéo.",
            "DECLINE": "J'ai compris.",
            "ACCEPT": "En savoir plus"
        },
        "COLORS": {
            "CANCEL_BUTTON": "Annuler",
            "BACKGROUND": "Arrière-plan",
            "TEXT": "Texte",
            "ADDITIONAL": "Transition",
            "PRESETS": "Pré-selection"
        },
        "PRESETS": {
            "CUSTOM_PRESET": "Template personnalisé",
            "PRESET_NAME": "Nom du Template ",
            "RANDOM": "Aléatoire",
            "SAVE_PRESET": "Sauvegarder un Template",
            "ADD_PRESET": "Ajouter un Template",
            "CHANNEL": "Compte",
            "SAVE_BUTTON": "Sauvegarder",
            "CANCEL_BUTTON": "Annuler"
        }
    },
    "VIDEO_PLAYER": {
        "DESCRIPTION_PLACEHOLDER": "Description",
        "SETTINGS": {
            "TITLE": "Paramètres",
            "AUTOPLAY_SWITCH_LABEL": "Autoplay",
            "MUTE_SWITCH_LABEL": "Autoplay (muet)",
            "CLOSE_SETTINGS": "Retour à l'édition"
        },
        "ADD_SECTION_TOOLTIP": "Vidéo Player"
    },
    "DELETE_SECTION_BTN": "Supprimer",
    "FLIP_CARD": {
        "ADD_SECTION_TOOLTIP": "Flip Card"
    },
    "QUIZ": {
        "DONE": "J'ai terminé",
        "INTRODUCTIONS": {
            "RESULTS": "Commencez par ajouter les résultats de votre Test de personnalité !",
            "QUESTIONS": "Maintenant créez des questions et associez-les à vos résultats"
        },
        "INTRO": {
            "TITLE": "Visuel",
            "PLACEHOLDER": "Titre du Test",
            "DESC_PLACEHOLDER": "Dites-en plus...",
            "CHANGE_STAGE": "Touches finales"
        },
        "QUESTIONS": {
            "TITLE": "Questions",
            "TITLE_SINGLE": "Question",
            "ADD": "Ajouter les questions",
            "ADD_ANOTHER": "Ajouter une autre question",
            "PLACEHOLDER": "Écrire la question ici...",
            "CHANGE_STAGE": "Retour aux questions"
        },
        "RESULTS": {
            "TITLE": "Résultats",
            "TITLE_SINGLE": "Résultat",
            "ADD": "Ajouter les résultats",
            "ADD_ANOTHER": "Ajouter un autre résultat",
            "PLACEHOLDER": "Ecrire le résultat ici...",
            "DESC_PLACEHOLDER": "Plus de détails",
            "CHANGE_STAGE": "Retour aux résultats"
        },
        "ANSWERS": {
            "TITLE": "Réponse",
            "ADD": "Ajouter une réponse",
            "ASSOCIATE": "Résultats associés",
            "LAYOUTS_TOOLTIPS": {
                "CLASSIC": "Classique",
                "GRID": "Grille"
            },
            "ASSOCIATION": [
                "Sans rapport",
                "Neutre",
                "En affinité"
            ],
            "ASSOCIATE_DESC": "Choisissez le résultat associé à cette réponse :",
            "MISSING_RESULTS": "Vous devez d'abord ajouter les résultats",
            "ASSOCIATE_PLURAL": "matched"
        },
        "REMOVE_ITEM": {
            "TITLE": "Êtes-vous sûr(e) ?",
            "DELETE_BUTTON_TEXT": "Supprimer",
            "TOOLTIP": "Supprimer"
        },
        "RESULT_ACTIONS": {
            "CTA": {
                "ADD": "Ajouter un Call To Action",
                "TOOLTIP": "Call-to-action",
                "PLACEHOLDER": "Entrer le texte..."
            },
            "CONTINUE": {
                "ADD": "Message du Call To Action",
                "TOOLTIP": "Continuer",
                "PLACEHOLDER": "Entrer le texte..."
            }
        },
        "ADD_SECTION_TOOLTIP": "Test de personnalité"
    },
    "MP_CUSTOM_TEMPLATE": {
        "EDIT_IMAGE_TITLE": "Éditer Image",
        "CROP_IMAGE_TITLE": "Recadrer",
        "EDIT_VIDEO_TITLE": "Éditer Vidéo",
        "NEW_LABEL": "NOUVEAU!"
    },
    "RESTORE_ITEM": {
        "TITLE": "On a assuré vos arrières ! 🤖",
        "DESCRIPTION": "Nous avons remarqué que des modifications ont été faites après la dernière publication de l'item. Voulez-vous restaurer les changements ?",
        "RESTORE_BUTTON": "Restaurer dans un nouvel onglet",
        "CANCEL_BUTTON": "Non merci!"
    },
    "DUPLICATE_SECTION_BTN": "Dupliquer",
    "TRIVIA": {
        "DONE": "Fini !",
        "INTRODUCTIONS": {
            "RESULTS": "Bon ou mauvais ? Finalisez les résultats de votre Trivia.",
            "QUESTIONS": "Créez votre première question !"
        },
        "QUESTIONS": {
            "TITLE": "Questions\n",
            "TITLE_SINGLE": "Question",
            "ADD": "Ajouter une question",
            "ADD_ANOTHER": "Ajouter une autre question",
            "PLACEHOLDER": "Ecrivez votre question ici...",
            "CHANGE_STAGE": "Ajouter une question"
        },
        "FEEDBACK": {
            "TITLE": "Commentaires",
            "PLACEHOLDER": "Commentez le résultat"
        },
        "RESULTS": {
            "TITLE": "Score final",
            "TITLE_SINGLE": "Résultat",
            "ADD": "Ajouter des résultats",
            "ADD_ANOTHER": "Ajouter un autre résultat",
            "PLACEHOLDER": "Dites leur comment ils s'en sont sortis",
            "DESC_PLACEHOLDER": "Commentaires",
            "CHANGE_STAGE": "Ajouter des résultats"
        },
        "ANSWERS": {
            "TITLE": "Réponse",
            "ADD": "Ajouter une réponse",
            "LAYOUTS_TOOLTIPS": {
                "CLASSIC": "Classique",
                "GRID": "Bloc"
            },
            "MISSING_RESULTS": "Vous devez commencer par ajouter des résultats !",
            "CORRECT_BUTTON": "Correcte"
        },
        "REMOVE_ITEM": {
            "TITLE": "Êtes-vous sûr ?",
            "DELETE_BUTTON_TEXT": "Supprimer",
            "TOOLTIP": "Supprimer"
        },
        "RESULT_ACTIONS": {
            "CTA": {
                "ADD": "Ajouter un \"call-to-action\"",
                "TOOLTIP": "Call-to-action",
                "PLACEHOLDER": "Ajouter du texte"
            },
            "CONTINUE": {
                "ADD": "Terminer avec un \"call-to-action\"",
                "TOOLTIP": "Continuer",
                "PLACEHOLDER": "Texte ici..."
            }
        },
        "ADD_SECTION_TOOLTIP": "Trivia",
        "MODES": {
            "TRIVIA": "Mode Trivia",
            "TRIVIA_DESCRIPTION": "Test de connaissance",
            "CHECKLIST": "Mode +1",
            "CHECKLIST_DESCRIPTION": "Comptage de points"
        },
        "BTN_INTRO_BUBBLE": {
            "NEW": "NOUVEAU !",
            "TITLE": "Quel monument est le plus grand ?",
            "DESC": "Améliorez votre engagement grâce au nouveau Trivia",
            "SHOW_ME": "Montrez-moi",
            "GOT_IT": "J'ai compris."
        }
    },
    "PREVIEW": {
        "DESKTOP": "Ordinateur",
        "TABLET": "Tablette",
        "MOBILE": "Mobile",
        "EMBED": "Copier le code Embed",
        "DRAFT_EMBED": "🤓  Oups - vous devez d'abord publier votre contenu !"
    },
    "CREATOR": {
        "TITLE_PLACEHOLDER": "Titre de la Story",
        "SECTIONS_LOBBY_TITLE": "Commencez à créer !",
        "SECTIONS_LOBBY_SUBTITLE": "Choisissez un des éléments ci-dessous ou",
        "SECTIONS_LOBBY_SUBTITLE_TEMPLATE": "utilisez un Template",
        "ADD_HEADER": "Ajouter l'en-tête",
        "ADD_MORE_STORY": "Ne vous arrêtez pas en si bon chemin !"
    },
    "MEDIA": {
        "BTN_INTRO_BUBBLE": {
            "NEW": "NOUVEAU !",
            "TITLE": "Insérer tous les médias ici !👇",
            "DESC": "Rechercher, télécharger, copier des liens à ajouter à vos créations vidéos, images, GIFS et posts.",
            "SHOW_ME": "Montrez moi !",
            "GOT_IT": "Compris"
        },
        "ADD_SECTION_TOOLTIP": "Média"
    }
}